{
  "type": "FeatureCollection",
  "features": [
    {
      "type": "Feature",
      "properties": {
        "CodZona": "116",
        "Zona": "Portelinha",
        "CodParagem": "396",
        "paragem": "396",
        "OrdemParagem": "1"
      },
      "geometry": {
        "coordinates": [
          -24.975097,
          16.872179
        ],
        "type": "Point"
      },
      "id": "09dfd10c-7601-421e-94cd-549cfba7a3bf"
    },
    {
      "type": "Feature",
      "properties": {
        "CodZona": "31",
        "Zona": "Estrada Principal CA",
        "CodParagem": "394",
        "paragem": "394",
        "OrdemParagem": "2"
      },
      "geometry": {
        "coordinates": [
          -24.977073,
          16.871222
        ],
        "type": "Point"
      },
      "id": "fd91399f-738a-452d-85dd-3bf4687adb50"
    },
    {
      "type": "Feature",
      "properties": {
        "CodZona": "57",
        "Zona": "Rua de Jardim Ribeira Craquinha",
        "CodParagem": "147",
        "paragem": "147",
        "OrdemParagem": "3"
      },
      "geometry": {
        "coordinates": [
          -24.9792008938179,
          16.870120734675
        ],
        "type": "Point"
      },
      "id": "97f9fad3-cb1e-40db-b445-39f66b67a9a0"
    },
    {
      "type": "Feature",
      "properties": {
        "CodZona": "87",
        "Zona": "Estrada Principal Fernando Po",
        "CodParagem": "148",
        "paragem": "148",
        "OrdemParagem": "4"
      },
      "geometry": {
        "coordinates": [
          -24.980295235096,
          16.8709703370412
        ],
        "type": "Point"
      },
      "id": "03cd011a-b472-4d9e-b750-4dd1b05f8250"
    },
    {
      "type": "Feature",
      "properties": {
        "CodZona": "87",
        "Zona": "Estrada Principal Fernando Po",
        "CodParagem": "149",
        "paragem": "149",
        "OrdemParagem": "5"
      },
      "geometry": {
        "coordinates": [
          -24.9809121431694,
          16.8727311321972
        ],
        "type": "Point"
      },
      "id": "dad1c4b2-f545-479f-aca5-8bb5dff890b5"
    },
    {
      "type": "Feature",
      "properties": {
        "CodZona": "83",
        "Zona": "Rua Principal de Fonte Frances",
        "CodParagem": "150",
        "paragem": "150",
        "OrdemParagem": "6"
      },
      "geometry": {
        "coordinates": [
          -24.9814298095093,
          16.8755955977032
        ],
        "type": "Point"
      },
      "id": "b50c98da-bb96-427c-a072-b3a934be30a4"
    },
    {
      "type": "Feature",
      "properties": {
        "CodZona": "83",
        "Zona": "Rua Principal de Fonte Frances",
        "CodParagem": "151",
        "paragem": "151",
        "OrdemParagem": "7"
      },
      "geometry": {
        "coordinates": [
          -24.9821271838532,
          16.8776027510525
        ],
        "type": "Point"
      },
      "id": "67b2923f-0db8-4136-9d31-9781da3279e2"
    },
    {
      "type": "Feature",
      "properties": {
        "CodZona": "49",
        "Zona": "Rua 2",
        "CodParagem": "152",
        "paragem": "152",
        "OrdemParagem": "8"
      },
      "geometry": {
        "coordinates": [
          -24.9842729510651,
          16.8768532794074
        ],
        "type": "Point"
      },
      "id": "867d503e-ca81-4b63-9933-1260bcc948de"
    },
    {
      "type": "Feature",
      "properties": {
        "CodZona": "13",
        "Zona": "Avenida de Hollanda",
        "CodParagem": "111",
        "paragem": "111",
        "OrdemParagem": "9"
      },
      "geometry": {
        "coordinates": [
          -24.9850802959786,
          16.8782675196458
        ],
        "type": "Point"
      },
      "id": "ccb1fced-e914-45c6-9c7a-1967fac1b939"
    },
    {
      "type": "Feature",
      "properties": {
        "CodZona": "13",
        "Zona": "Avenida de Hollanda",
        "CodParagem": "154",
        "paragem": "154",
        "OrdemParagem": "10"
      },
      "geometry": {
        "coordinates": [
          -24.985887640892,
          16.8799178809791
        ],
        "type": "Point"
      },
      "id": "102c8f5c-a55a-48b6-a99e-4535604029af"
    },
    {
      "type": "Feature",
      "properties": {
        "CodZona": "10",
        "Zona": "Rua de Praia",
        "CodParagem": "155",
        "paragem": "155",
        "OrdemParagem": "11"
      },
      "geometry": {
        "coordinates": [
          -24.9872126521454,
          16.8817889574847
        ],
        "type": "Point"
      },
      "id": "f5194c78-b921-4d90-9efb-86247169c06a"
    },
    {
      "type": "Feature",
      "properties": {
        "CodZona": "92",
        "Zona": "Zona de Praça Estrela",
        "CodParagem": "73",
        "paragem": "73",
        "OrdemParagem": "12"
      },
      "geometry": {
        "coordinates": [
          -24.9883016290054,
          16.8827668378279
        ],
        "type": "Point"
      },
      "id": "1ce38fb9-9e42-462b-94f4-b194bb9c6fc0"
    },
    {
      "type": "Feature",
      "properties": {
        "CodZona": "92",
        "Zona": "Zona de Praça Estrela",
        "CodParagem": "74",
        "paragem": "74",
        "OrdemParagem": "13"
      },
      "geometry": {
        "coordinates": [
          -24.989846581398,
          16.8833853894454
        ],
        "type": "Point"
      },
      "id": "60fe4070-0537-4a83-b748-b423a155111e"
    },
    {
      "type": "Feature",
      "properties": {
        "CodZona": "88",
        "Zona": "Praça Dom Luis",
        "CodParagem": "75",
        "paragem": "75",
        "OrdemParagem": "14"
      },
      "geometry": {
        "coordinates": [
          -24.9891518892632,
          16.8862265942821
        ],
        "type": "Point"
      },
      "id": "77c1af36-b163-47ca-ab27-918d4f39c245"
    },
    {
      "type": "Feature",
      "properties": {
        "CodZona": "25",
        "Zona": "Praça Nho Roque",
        "CodParagem": "27",
        "paragem": "27",
        "OrdemParagem": "15"
      },
      "geometry": {
        "coordinates": [
          -24.9892833175049,
          16.8877074943915
        ],
        "type": "Point"
      },
      "id": "2007844c-2337-4ee1-b704-6fbad5e0b997"
    },
    {
      "type": "Feature",
      "properties": {
        "CodZona": "2",
        "Zona": "Avenida Marginal",
        "CodParagem": "28",
        "paragem": "28",
        "OrdemParagem": "16"
      },
      "geometry": {
        "coordinates": [
          -24.991107219635,
          16.8891524515821
        ],
        "type": "Point"
      },
      "id": "a7eb7cf5-042e-4c0f-8abb-d16e4aac3b3a"
    },
    {
      "type": "Feature",
      "properties": {
        "CodZona": "2",
        "Zona": "Avenida Marginal",
        "CodParagem": "29",
        "paragem": "29",
        "OrdemParagem": "17"
      },
      "geometry": {
        "coordinates": [
          -24.9925582947121,
          16.8892217476524
        ],
        "type": "Point"
      },
      "id": "70fd0406-ff5f-4c46-a1a4-2cb9a5194ae6"
    },
    {
      "type": "Feature",
      "properties": {
        "CodZona": "2",
        "Zona": "Avenida Marginal",
        "CodParagem": "30",
        "paragem": "30",
        "OrdemParagem": "18"
      },
      "geometry": {
        "coordinates": [
          -24.9937599243507,
          16.8901251607601
        ],
        "type": "Point"
      },
      "id": "ded49e60-36da-4778-948d-6696eb13011c"
    },
    {
      "type": "Feature",
      "properties": {
        "CodZona": "2",
        "Zona": "Avenida Marginal",
        "CodParagem": "31",
        "paragem": "31",
        "OrdemParagem": "19"
      },
      "geometry": {
        "coordinates": [
          -24.9926682652817,
          16.8929226341424
        ],
        "type": "Point"
      },
      "id": "7eb23ab2-20c9-4992-8e72-e6f396a49163"
    },
    {
      "type": "Feature",
      "properties": {
        "CodZona": "110",
        "Zona": "Laginha",
        "CodParagem": "32",
        "paragem": "32",
        "OrdemParagem": "20"
      },
      "geometry": {
        "coordinates": [
          -24.9916597546921,
          16.8958201568769
        ],
        "type": "Point"
      },
      "id": "f9ba2de3-5cb0-475e-b6f6-24ae3c264d3c"
    },
    {
      "type": "Feature",
      "properties": {
        "CodZona": "37",
        "Zona": "Rua de Casa Bau",
        "CodParagem": "33",
        "paragem": "33",
        "OrdemParagem": "21"
      },
      "geometry": {
        "coordinates": [
          -24.9906512441025,
          16.8963642394422
        ],
        "type": "Point"
      },
      "id": "a8830f04-27ba-460e-ae05-da8054b54c2b"
    },
    {
      "type": "Feature",
      "properties": {
        "CodZona": "37",
        "Zona": "Rua de Casa Bau",
        "CodParagem": "34",
        "paragem": "34",
        "OrdemParagem": "22"
      },
      "geometry": {
        "coordinates": [
          -24.9893798770294,
          16.8967825660078
        ],
        "type": "Point"
      },
      "id": "8b37c98d-e537-4ad1-bde2-c4def87634e5"
    },
    {
      "type": "Feature",
      "properties": {
        "CodZona": "27",
        "Zona": "Bairro Cha Alecrim",
        "CodParagem": "35",
        "paragem": "35",
        "OrdemParagem": "23"
      },
      "geometry": {
        "coordinates": [
          -24.9885162057266,
          16.897367708359
        ],
        "type": "Point"
      },
      "id": "f964f890-f6fb-4714-8c2d-749d8ac12507"
    },
    {
      "type": "Feature",
      "properties": {
        "CodZona": "31",
        "Zona": "Estrada Principal CA",
        "CodParagem": "36",
        "paragem": "36",
        "OrdemParagem": "24"
      },
      "geometry": {
        "coordinates": [
          -24.987360173641264,
          16.898509757280376
        ],
        "type": "Point"
      },
      "id": "8e6cf0c5-4782-45d0-90f5-b605dd8891ea"
    },
    {
      "type": "Feature",
      "properties": {
        "CodZona": "31",
        "Zona": "Estrada Principal CA",
        "CodParagem": "98",
        "paragem": "98",
        "OrdemParagem": "25"
      },
      "geometry": {
        "coordinates": [
          -24.98834990876776,
          16.898555952372053
        ],
        "type": "Point"
      },
      "id": "178f51c0-596a-4a08-ae7b-f655f1559fb9"
    },
    {
      "type": "Feature",
      "properties": {
        "CodZona": "31",
        "Zona": "Estrada Principal CA",
        "CodParagem": "2",
        "paragem": "2",
        "OrdemParagem": "26"
      },
      "geometry": {
        "coordinates": [
          -24.9903347434387,
          16.8977013413431
        ],
        "type": "Point"
      },
      "id": "3c5addd7-818e-4f90-a5f4-6160f0cad1a1"
    },
    {
      "type": "Feature",
      "properties": {
        "CodZona": "110",
        "Zona": "Laginha",
        "CodParagem": "3",
        "paragem": "3",
        "OrdemParagem": "27"
      },
      "geometry": {
        "coordinates": [
          -24.9918796958313,
          16.895658471661
        ],
        "type": "Point"
      },
      "id": "df6664a9-5125-4b9d-bee1-a38e9e4af83f"
    },
    {
      "type": "Feature",
      "properties": {
        "CodZona": "110",
        "Zona": "Laginha",
        "CodParagem": "4",
        "paragem": "4",
        "OrdemParagem": "28"
      },
      "geometry": {
        "coordinates": [
          -24.9924536885605,
          16.893687440746
        ],
        "type": "Point"
      },
      "id": "5cb3eb76-3ee7-4a41-99e2-2f13950048c3"
    },
    {
      "type": "Feature",
      "properties": {
        "CodZona": "2",
        "Zona": "Avenida Marginal",
        "CodParagem": "5",
        "paragem": "5",
        "OrdemParagem": "29"
      },
      "geometry": {
        "coordinates": [
          -24.9938323439942,
          16.8898839088193
        ],
        "type": "Point"
      },
      "id": "98da4187-3242-400f-818a-2d1d33416a3b"
    },
    {
      "type": "Feature",
      "properties": {
        "CodZona": "2",
        "Zona": "Avenida Marginal",
        "CodParagem": "6",
        "paragem": "6",
        "OrdemParagem": "30"
      },
      "geometry": {
        "coordinates": [
          -24.9923946799622,
          16.8889933271759
        ],
        "type": "Point"
      },
      "id": "751a0787-4266-49da-b310-88361583b5cd"
    },
    {
      "type": "Feature",
      "properties": {
        "CodZona": "2",
        "Zona": "Avenida Marginal",
        "CodParagem": "7",
        "paragem": "7",
        "OrdemParagem": "31"
      },
      "geometry": {
        "coordinates": [
          -24.9896534623489,
          16.8881720377855
        ],
        "type": "Point"
      },
      "id": "4cd6ab36-9c1f-4de0-957d-e124ef39b876"
    },
    {
      "type": "Feature",
      "properties": {
        "CodZona": "10",
        "Zona": "Rua de Praia",
        "CodParagem": "54",
        "paragem": "54",
        "OrdemParagem": "32"
      },
      "geometry": {
        "coordinates": [
          -24.9893476905213,
          16.8862240277206
        ],
        "type": "Point"
      },
      "id": "e9f1bf7c-7161-4e6d-9b2c-9ab32cd0898b"
    },
    {
      "type": "Feature",
      "properties": {
        "CodZona": "10",
        "Zona": "Rua de Praia",
        "CodParagem": "55",
        "paragem": "55",
        "OrdemParagem": "33"
      },
      "geometry": {
        "coordinates": [
          -24.9898090304718,
          16.8846122202668
        ],
        "type": "Point"
      },
      "id": "d260a350-6dc6-43c0-b2de-40999e368470"
    },
    {
      "type": "Feature",
      "properties": {
        "CodZona": "92",
        "Zona": "Zona de Praça Estrela",
        "CodParagem": "56",
        "paragem": "56",
        "OrdemParagem": "34"
      },
      "geometry": {
        "coordinates": [
          -24.9883289149295,
          16.8826771813208
        ],
        "type": "Point"
      },
      "id": "5b84b487-26e3-49c2-8047-3cd22e20b175"
    },
    {
      "type": "Feature",
      "properties": {
        "CodZona": "30",
        "Zona": "Atras de Cadeia",
        "CodParagem": "251",
        "paragem": "251",
        "OrdemParagem": "35"
      },
      "geometry": {
        "coordinates": [
          -24.9871777834282,
          16.8811396010727
        ],
        "type": "Point"
      },
      "id": "f733d416-88cc-4a8b-beae-7353c936ee27"
    },
    {
      "type": "Feature",
      "properties": {
        "CodZona": "13",
        "Zona": "Avenida de Hollanda",
        "CodParagem": "164",
        "paragem": "164",
        "OrdemParagem": "36"
      },
      "geometry": {
        "coordinates": [
          -24.9860861243591,
          16.8799820471471
        ],
        "type": "Point"
      },
      "id": "36d4e7d2-b834-4629-a2a5-4b71fa12e28d"
    },
    {
      "type": "Feature",
      "properties": {
        "CodZona": "14",
        "Zona": "Rua 1",
        "CodParagem": "165",
        "paragem": "165",
        "OrdemParagem": "37"
      },
      "geometry": {
        "coordinates": [
          -24.9855096312688,
          16.8776298335745
        ],
        "type": "Point"
      },
      "id": "e8a3b9b9-1de2-4f47-bccd-3adb428f5b72"
    },
    {
      "type": "Feature",
      "properties": {
        "CodZona": "49",
        "Zona": "Rua 2",
        "CodParagem": "166",
        "paragem": "166",
        "OrdemParagem": "38"
      },
      "geometry": {
        "coordinates": [
          -24.9843453707085,
          16.8768224791392
        ],
        "type": "Point"
      },
      "id": "1e8a6b92-4858-41f6-9821-737a959cddd4"
    },
    {
      "type": "Feature",
      "properties": {
        "CodZona": "83",
        "Zona": "Rua Principal de Fonte Frances",
        "CodParagem": "167",
        "paragem": "167",
        "OrdemParagem": "39"
      },
      "geometry": {
        "coordinates": [
          -24.9823042096481,
          16.8777721517657
        ],
        "type": "Point"
      },
      "id": "5c295d2c-cc2a-448c-8257-71f076e5ebd0"
    },
    {
      "type": "Feature",
      "properties": {
        "CodZona": "83",
        "Zona": "Rua Principal de Fonte Frances",
        "CodParagem": "168",
        "paragem": "168",
        "OrdemParagem": "40"
      },
      "geometry": {
        "coordinates": [
          -24.9816551150665,
          16.8759985700999
        ],
        "type": "Point"
      },
      "id": "7c58aab4-1884-4cfa-8cc6-3bbdcc9a3af6"
    },
    {
      "type": "Feature",
      "properties": {
        "CodZona": "87",
        "Zona": "Estrada Principal Fernando Po",
        "CodParagem": "169",
        "paragem": "169",
        "OrdemParagem": "41"
      },
      "geometry": {
        "coordinates": [
          -24.9813627542839,
          16.8731572113577
        ],
        "type": "Point"
      },
      "id": "0665b8d7-90f4-412d-aec3-1acbaac2cc42"
    },
    {
      "type": "Feature",
      "properties": {
        "CodZona": "31",
        "Zona": "Estrada Principal CA",
        "CodParagem": "170",
        "paragem": "170",
        "OrdemParagem": "42"
      },
      "geometry": {
        "coordinates": [
          -24.980391794620573,
          16.87120647961872
        ],
        "type": "Point"
      },
      "id": "2cc4e878-2259-4668-af21-90da1bfeb2d7"
    },
    {
      "type": "Feature",
      "properties": {
        "CodZona": "45",
        "Zona": "Estrada Principal RC",
        "CodParagem": "393",
        "paragem": "393",
        "OrdemParagem": "43"
      },
      "geometry": {
        "coordinates": [
          -24.978456,
          16.870508
        ],
        "type": "Point"
      },
      "id": "57df926e-a10a-4161-9454-e1deecca2b01"
    },
    {
      "type": "Feature",
      "properties": {
        "CodZona": "31",
        "Zona": "Estrada Principal CA",
        "CodParagem": "395",
        "paragem": "395",
        "OrdemParagem": "44"
      },
      "geometry": {
        "coordinates": [
          -24.976931,
          16.871195
        ],
        "type": "Point"
      },
      "id": "8e7cbc2f-4ed2-422b-b22c-6803c35ca892"
    },
    {
      "type": "Feature",
      "properties": {
        "Cor_linha_css": "#FFFF00"
      },
      "geometry": {
        "coordinates": [
          [
            -24.987395509354656,
            16.898536157830822
          ],
          [
            -24.98742501365382,
            16.898692707796247
          ],
          [
            -24.988004370801036,
            16.898613149633334
          ],
          [
            -24.98811702357966,
            16.898592618489072
          ],
          [
            -24.988194807641094,
            16.898574653735995
          ],
          [
            -24.990305706135814,
            16.89765588265481
          ],
          [
            -24.990536376111095,
            16.897555792797405
          ],
          [
            -24.990584655873363,
            16.897558359204663
          ],
          [
            -24.990635617844646,
            16.89756862483337
          ],
          [
            -24.990673168770854,
            16.89757632405454
          ],
          [
            -24.990716084115093,
            16.89758658968227
          ],
          [
            -24.99076972829539,
            16.897584023275382
          ],
          [
            -24.990804597012584,
            16.897566058426253
          ],
          [
            -24.990826054684703,
            16.897542960760553
          ],
          [
            -24.990844830147807,
            16.897509597460683
          ],
          [
            -24.990852876774852,
            16.897478800563253
          ],
          [
            -24.990850194565837,
            16.89745057006954
          ],
          [
            -24.990842147938793,
            16.897419773162465
          ],
          [
            -24.990839465729778,
            16.89738897625038
          ],
          [
            -24.990839465729778,
            16.897360745743207
          ],
          [
            -24.990836783520763,
            16.89731455035871
          ],
          [
            -24.990847512356822,
            16.89701171366911
          ],
          [
            -24.990871652237956,
            16.896901357805408
          ],
          [
            -24.99090652095515,
            16.896798701130038
          ],
          [
            -24.990960165135448,
            16.89667551304586
          ],
          [
            -24.99101649152476,
            16.89659595403206
          ],
          [
            -24.991072817914073,
            16.896534359933835
          ],
          [
            -24.991603895299022,
            16.896049305707326
          ],
          [
            -24.991649492852275,
            16.89599797714476
          ],
          [
            -24.991687043778484,
            16.895949214997383
          ],
          [
            -24.991719230286662,
            16.89589275354785
          ],
          [
            -24.991743370167796,
            16.89583629208141
          ],
          [
            -24.991770192257945,
            16.895777264166615
          ],
          [
            -24.991791649930065,
            16.89565407541535
          ],
          [
            -24.99193112479884,
            16.8950868928352
          ],
          [
            -24.99249170648295,
            16.893398167182557
          ],
          [
            -24.992558761708324,
            16.893254445152415
          ],
          [
            -24.992926224343364,
            16.892705220671466
          ],
          [
            -24.993215902916972,
            16.892407509536927
          ],
          [
            -24.993331237904613,
            16.892279185627167
          ],
          [
            -24.99341170417506,
            16.892145728668424
          ],
          [
            -24.993473394982402,
            16.891999439201353
          ],
          [
            -24.99349485265452,
            16.89192244469944
          ],
          [
            -24.993728204838817,
            16.891568269585974
          ],
          [
            -24.993830128781383,
            16.89144251159589
          ],
          [
            -24.99391595946986,
            16.89129365509114
          ],
          [
            -24.993977650277202,
            16.89115249795229
          ],
          [
            -24.994012518994396,
            16.891049838148618
          ],
          [
            -24.99403665887553,
            16.89094204529465
          ],
          [
            -24.99405811654765,
            16.890806020891056
          ],
          [
            -24.994055434338634,
            16.890698227897804
          ],
          [
            -24.994050069920604,
            16.890598134348938
          ],
          [
            -24.994033976666515,
            16.89050574025669
          ],
          [
            -24.99400983678538,
            16.890408213110245
          ],
          [
            -24.993980332486217,
            16.89030811940753
          ],
          [
            -24.99394278156001,
            16.89022342469454
          ],
          [
            -24.993819399945323,
            16.889933409177246
          ],
          [
            -24.99374161588389,
            16.889776851942827
          ],
          [
            -24.993682607285564,
            16.88967675790522
          ],
          [
            -24.993586047761028,
            16.88955613168679
          ],
          [
            -24.99348412381846,
            16.88945347101462
          ],
          [
            -24.99340633975703,
            16.889389308066153
          ],
          [
            -24.99331782685954,
            16.88933541117259
          ],
          [
            -24.993231996171062,
            16.88928664730324
          ],
          [
            -24.993151529900615,
            16.889248149502734
          ],
          [
            -24.993041559331004,
            16.88920965169439
          ],
          [
            -24.99281893598277,
            16.889148055184695
          ],
          [
            -24.99255607949931,
            16.889073626041977
          ],
          [
            -24.99225567208964,
            16.888994063822494
          ],
          [
            -24.99200354444224,
            16.888929900717827
          ],
          [
            -24.991874798409526,
            16.888906801994807
          ],
          [
            -24.991754099003856,
            16.88890936851972
          ],
          [
            -24.991590484253948,
            16.888917068094287
          ],
          [
            -24.991424187295024,
            16.88894786638933
          ],
          [
            -24.99125252591807,
            16.888983797727214
          ],
          [
            -24.991099640004222,
            16.888999196869925
          ],
          [
            -24.990954800717418,
            16.88900432991722
          ],
          [
            -24.99081800805766,
            16.888994063822494
          ],
          [
            -24.99064366447169,
            16.8889606990108
          ],
          [
            -24.990482731930797,
            16.88892733419318
          ],
          [
            -24.990343257062023,
            16.888883703268963
          ],
          [
            -24.99024401532847,
            16.888834939282887
          ],
          [
            -24.990101858250682,
            16.88874767738161
          ],
          [
            -24.989967747799938,
            16.888645016269635
          ],
          [
            -24.989868506066387,
            16.88853722204196
          ],
          [
            -24.98973976003367,
            16.88839862937304
          ],
          [
            -24.98964588271815,
            16.888272869270573
          ],
          [
            -24.98957346307475,
            16.888162508295284
          ],
          [
            -24.98951445447642,
            16.888054713792013
          ],
          [
            -24.98944739925105,
            16.887872489610732
          ],
          [
            -24.98940448390681,
            16.88772363028982
          ],
          [
            -24.9893669329806,
            16.88757990393753
          ],
          [
            -24.989334746472423,
            16.88742847784081
          ],
          [
            -24.98930524217326,
            16.887264218886678
          ],
          [
            -24.98927842008311,
            16.887110225987318
          ],
          [
            -24.989265009038036,
            16.88697163227048
          ],
          [
            -24.989265009038036,
            16.886897202269434
          ],
          [
            -24.98927305566508,
            16.88686897019238
          ],
          [
            -24.98928378450114,
            16.88682277223903
          ],
          [
            -24.989291831128185,
            16.886784273935934
          ],
          [
            -24.98930524217326,
            16.886748342179285
          ],
          [
            -24.989307924382274,
            16.886712410415793
          ],
          [
            -24.989313288800304,
            16.886679045200708
          ],
          [
            -24.989307924382274,
            16.8866482465354
          ],
          [
            -24.989297195546214,
            16.88661488130898
          ],
          [
            -24.989286466710155,
            16.88656868329342
          ],
          [
            -24.98927842008311,
            16.886543017724353
          ],
          [
            -24.989270373456065,
            16.88637105832147
          ],
          [
            -24.98926769124705,
            16.886265829355875
          ],
          [
            -24.989275737874095,
            16.886147767519763
          ],
          [
            -24.98928914891917,
            16.88604767155739
          ],
          [
            -24.989307924382274,
            16.885932176150227
          ],
          [
            -24.989324017636363,
            16.885857745739273
          ],
          [
            -24.989369615189617,
            16.885637020899736
          ],
          [
            -24.98950372564036,
            16.885277700841403
          ],
          [
            -24.98953054773051,
            16.885221236198618
          ],
          [
            -24.98965661155421,
            16.884864481928716
          ],
          [
            -24.989798768632,
            16.884415329910674
          ],
          [
            -24.9901769601031,
            16.883339927307745
          ],
          [
            -24.98881708013255,
            16.882852272557237
          ],
          [
            -24.988355740181987,
            16.88269314283976
          ],
          [
            -24.98817603217799,
            16.882621277762077
          ],
          [
            -24.98806606160838,
            16.882551979268413
          ],
          [
            -24.988004370801036,
            16.88249294719819
          ],
          [
            -24.987942679993694,
            16.882413382204767
          ],
          [
            -24.98757253514964,
            16.88176659456245
          ],
          [
            -24.9874888033562,
            16.881542615935427
          ],
          [
            -24.98737883278659,
            16.881273120110787
          ],
          [
            -24.986810204475432,
            16.881152488521806
          ],
          [
            -24.986676094024688,
            16.881090889382797
          ],
          [
            -24.986630496471435,
            16.88106008980577
          ],
          [
            -24.986576852291137,
            16.881008757166203
          ],
          [
            -24.985906300037414,
            16.879728003291316
          ],
          [
            -24.98564076134494,
            16.879189006077333
          ],
          [
            -24.985632714717894,
            16.87913510627132
          ],
          [
            -24.98562466809085,
            16.879078639791373
          ],
          [
            -24.9855978460007,
            16.879037573249896
          ],
          [
            -24.985544201820403,
            16.878999073359154
          ],
          [
            -24.985053357570678,
            16.878051973575165
          ],
          [
            -24.98549860426715,
            16.87741800439914
          ],
          [
            -24.984790501087218,
            16.876889267345348
          ],
          [
            -24.98465370842746,
            16.877058668698506
          ],
          [
            -24.983773943870574,
            16.87642982957719
          ],
          [
            -24.983554002731353,
            16.87666596532946
          ],
          [
            -24.983221408813506,
            16.87696370129196
          ],
          [
            -24.983100709407836,
            16.8770869022426
          ],
          [
            -24.98272520014575,
            16.87759510531436
          ],
          [
            -24.982349690883666,
            16.877913373208333
          ],
          [
            -24.982081469982177,
            16.877307637078136
          ],
          [
            -24.981909808605224,
            16.876904667474644
          ],
          [
            -24.981783744781524,
            16.876501697011317
          ],
          [
            -24.981558439224273,
            16.87575992110785
          ],
          [
            -24.981394824474364,
            16.875356948202064
          ],
          [
            -24.981394824474364,
            16.87416599140429
          ],
          [
            -24.981410917728454,
            16.873996587456634
          ],
          [
            -24.981461879699737,
            16.873806649516496
          ],
          [
            -24.98151820608905,
            16.873578210389553
          ],
          [
            -24.98147529074481,
            16.873419072856965
          ],
          [
            -24.98137068459323,
            16.873200900215355
          ],
          [
            -24.98103540846637,
            16.872808188825488
          ],
          [
            -24.98099785754016,
            16.8727594206874
          ],
          [
            -24.98071890780261,
            16.87216906854353
          ],
          [
            -24.980464097946196,
            16.8717250198457
          ],
          [
            -24.980431911438018,
            16.87164801707515
          ],
          [
            -24.980413135974914,
            16.871581281315276
          ],
          [
            -24.980397042720824,
            16.871517112293173
          ],
          [
            -24.9803568095856,
            16.870677779477035
          ],
          [
            -24.980343398540526,
            16.870544307248256
          ],
          [
            -24.980313,
            16.870335
          ],
          [
            -24.9796,
            16.869772
          ],
          [
            -24.97868,
            16.870389
          ],
          [
            -24.977883,
            16.870824
          ],
          [
            -24.97584,
            16.871591
          ],
          [
            -24.975875,
            16.871655
          ],
          [
            -24.977872,
            16.870891
          ],
          [
            -24.978667,
            16.870476
          ],
          [
            -24.979609,
            16.869877
          ],
          [
            -24.980078,
            16.870217
          ],
          [
            -24.980255,
            16.870387
          ],
          [
            -24.98029511877826,
            16.87056997499188
          ],
          [
            -24.980313894241363,
            16.870816385153255
          ],
          [
            -24.9803568095856,
            16.871578714554815
          ],
          [
            -24.980675992458373,
            16.872199869570572
          ],
          [
            -24.980936166732818,
            16.872756853942942
          ],
          [
            -24.980979082077056,
            16.872826156031078
          ],
          [
            -24.98133313366702,
            16.873241968025976
          ],
          [
            -24.98140287110141,
            16.873388272028727
          ],
          [
            -24.981443104236632,
            16.87349864164001
          ],
          [
            -24.98146456190875,
            16.87359104405569
          ],
          [
            -24.981461879699737,
            16.873614144652553
          ],
          [
            -24.9813653201752,
            16.873940119440324
          ],
          [
            -24.98134922692111,
            16.874055622182915
          ],
          [
            -24.981335815876037,
            16.875295347172532
          ],
          [
            -24.981341180294066,
            16.875362081620274
          ],
          [
            -24.98148065516284,
            16.875711153731874
          ],
          [
            -24.98176496931842,
            16.876606931419087
          ],
          [
            -24.98185348221591,
            16.876884133968638
          ],
          [
            -24.982180711715728,
            16.877682372370945
          ],
          [
            -24.982344326465636,
            16.878013473483488
          ],
          [
            -24.982623276203185,
            16.87775937268148
          ],
          [
            -24.98275738665393,
            16.877636172169552
          ],
          [
            -24.98314630696109,
            16.87710743572657
          ],
          [
            -24.98360228249362,
            16.876694198932295
          ],
          [
            -24.983792719333678,
            16.87650939709194
          ],
          [
            -24.984718081443816,
            16.877189569640063
          ],
          [
            -24.9852732987099,
            16.87761820542152
          ],
          [
            -24.98496216246417,
            16.87806994028195
          ],
          [
            -24.985447642295867,
            16.87899650669949
          ],
          [
            -24.985453006713897,
            16.87902473995386
          ],
          [
            -24.985444960086852,
            16.879073506474192
          ],
          [
            -24.985444960086852,
            16.87910430637526
          ],
          [
            -24.985474464386016,
            16.87916333950498
          ],
          [
            -24.985501286476165,
            16.87918130610601
          ],
          [
            -24.98553615519336,
            16.879189006077347
          ],
          [
            -24.985568341701537,
            16.879219805959586
          ],
          [
            -24.986432013004332,
            16.880882992140315
          ],
          [
            -24.986563441246062,
            16.88109602264517
          ],
          [
            -24.986767289131194,
            16.881198687862884
          ],
          [
            -24.986686822860747,
            16.881640147662903
          ],
          [
            -24.98719912478259,
            16.881740245962373
          ],
          [
            -24.987542447536498,
            16.881853177313435
          ],
          [
            -24.98789381691745,
            16.882458898861792
          ],
          [
            -24.987915274589568,
            16.88249483143495
          ],
          [
            -24.987936732261687,
            16.882525630777938
          ],
          [
            -24.98796087214282,
            16.882551296893258
          ],
          [
            -24.987993058651,
            16.88258209622702
          ],
          [
            -24.988027927368194,
            16.882612895555756
          ],
          [
            -24.988070842712432,
            16.882638561659206
          ],
          [
            -24.988132533519774,
            16.882671927588476
          ],
          [
            -24.988194224327117,
            16.88270529351184
          ],
          [
            -24.988331016986876,
            16.88275919229869
          ],
          [
            -24.988636788814574,
            16.882879822861074
          ],
          [
            -24.990106639354735,
            16.88340340994065
          ],
          [
            -24.989760634391814,
            16.884360749228097
          ],
          [
            -24.989519235580474,
            16.885084525305647
          ],
          [
            -24.989293930023223,
            16.885682536779495
          ],
          [
            -24.98923223921588,
            16.885985391652966
          ],
          [
            -24.9892000527077,
            16.88619841639997
          ],
          [
            -24.98914372631839,
            16.886680929395716
          ],
          [
            -24.989151772945434,
            16.88674252671064
          ],
          [
            -24.989170548408538,
            16.88678615812987
          ],
          [
            -24.989175912826568,
            16.886832356092203
          ],
          [
            -24.989253696888,
            16.887407263121787
          ],
          [
            -24.989285883396178,
            16.887571521951422
          ],
          [
            -24.989323434322387,
            16.88770241560396
          ],
          [
            -24.989387807338744,
            16.887946236871517
          ],
          [
            -24.98945754477313,
            16.88814129365875
          ],
          [
            -24.98952728220752,
            16.88828501958352
          ],
          [
            -24.989618477314025,
            16.888408213146178
          ],
          [
            -24.989706990211516,
            16.888505741326266
          ],
          [
            -24.990044948547393,
            16.888808591669466
          ],
          [
            -24.990173694580108,
            16.888900986592677
          ],
          [
            -24.990318533866912,
            16.888980548851407
          ],
          [
            -24.99044459769061,
            16.889013913659607
          ],
          [
            -24.990554568260222,
            16.88904214541577
          ],
          [
            -24.990694043128997,
            16.889070377167723
          ],
          [
            -24.990820106952697,
            16.889090909348315
          ],
          [
            -24.990924713104278,
            16.889098608915454
          ],
          [
            -24.991021272628814,
            16.88910117543777
          ],
          [
            -24.99111783215335,
            16.88910117543777
          ],
          [
            -24.991214391677886,
            16.889088342825854
          ],
          [
            -24.991340455501586,
            16.889065244122225
          ],
          [
            -24.991450426071196,
            16.889039578892653
          ],
          [
            -24.991557714431792,
            16.889016480183066
          ],
          [
            -24.991635498493224,
            16.889013913659607
          ],
          [
            -24.991745469062835,
            16.889013913659607
          ],
          [
            -24.991844710796386,
            16.88901904670649
          ],
          [
            -24.991933223693877,
            16.889029312799853
          ],
          [
            -24.992067334144622,
            16.889052411507883
          ],
          [
            -24.99294978091052,
            16.889296231031288
          ],
          [
            -24.993030247180968,
            16.88932189622594
          ],
          [
            -24.993121442287475,
            16.889357827492603
          ],
          [
            -24.99319654413989,
            16.8893911922341
          ],
          [
            -24.993252870529204,
            16.889421990451783
          ],
          [
            -24.993341383426696,
            16.889478453837803
          ],
          [
            -24.993435260742217,
            16.88957084843306
          ],
          [
            -24.993553277938872,
            16.88968890812779
          ],
          [
            -24.993660566299468,
            16.889865997531416
          ],
          [
            -24.99374907919696,
            16.890035387240246
          ],
          [
            -24.993893918483764,
            16.890348501150186
          ],
          [
            -24.993944880455047,
            16.890512757419767
          ],
          [
            -24.99395829150012,
            16.890664181041622
          ],
          [
            -24.993960973709136,
            16.89078993955044
          ],
          [
            -24.993955609291106,
            16.890918264473054
          ],
          [
            -24.993934151618987,
            16.891056855291463
          ],
          [
            -24.993907329528838,
            16.89115951509132
          ],
          [
            -24.993861731975585,
            16.891275007299395
          ],
          [
            -24.99381613442233,
            16.891375100489203
          ],
          [
            -24.99372225710681,
            16.891503425013852
          ],
          [
            -24.993684706180602,
            16.891557321288175
          ],
          [
            -24.993539866893798,
            16.891734408938284
          ],
          [
            -24.993483540504485,
            16.891839634854566
          ],
          [
            -24.99344330736926,
            16.891962826096616
          ],
          [
            -24.993408438652068,
            16.89207061836742
          ],
          [
            -24.993373569934874,
            16.892157878732018
          ],
          [
            -24.993311879127532,
            16.892247705535777
          ],
          [
            -24.99321800181201,
            16.89234779820957
          ],
          [
            -24.993110713451415,
            16.892445324353492
          ],
          [
            -24.993000742881804,
            16.892527451593484
          ],
          [
            -24.992896136730224,
            16.892617278221284
          ],
          [
            -24.99283444592288,
            16.892699405386406
          ],
          [
            -24.992727157562285,
            16.89287649196458
          ],
          [
            -24.99260914036563,
            16.893040746033428
          ],
          [
            -24.992458936660796,
            16.893128005949336
          ],
          [
            -24.99238919922641,
            16.893174202359077
          ],
          [
            -24.9923516483002,
            16.893220398757492
          ],
          [
            -24.99233555504611,
            16.893264028678946
          ],
          [
            -24.992338237255126,
            16.89332819030981
          ],
          [
            -24.9923516483002,
            16.89336668727785
          ],
          [
            -24.99236774155429,
            16.893420583019925
          ],
          [
            -24.992386517017394,
            16.893477045209398
          ],
          [
            -24.99239456364444,
            16.893510409222497
          ],
          [
            -24.991941270320922,
            16.894886028010394
          ],
          [
            -24.991833981960326,
            16.895294092102283
          ],
          [
            -24.99176424452594,
            16.895550735733064
          ],
          [
            -24.99172669359973,
            16.89571498747352
          ],
          [
            -24.99169450709155,
            16.895799679721286
          ],
          [
            -24.99160599419406,
            16.895956231958
          ],
          [
            -24.991544303386718,
            16.896012693388553
          ],
          [
            -24.991482612579375,
            16.896069154802184
          ],
          [
            -24.990951535194426,
            16.896531111188047
          ],
          [
            -24.99053042837909,
            16.896328363802457
          ],
          [
            -24.990468737571746,
            16.896312965257927
          ],
          [
            -24.990385589092284,
            16.89630269956089
          ],
          [
            -24.990289029567748,
            16.896305265985195
          ],
          [
            -24.990221974342376,
            16.896325797378445
          ],
          [
            -24.99015760132602,
            16.896341195921917
          ],
          [
            -24.98939048954776,
            16.89673385835573
          ],
          [
            -24.989293930023223,
            16.89676722179282
          ],
          [
            -24.989213463752776,
            16.89677748746458
          ],
          [
            -24.98913299748233,
            16.89677235462877
          ],
          [
            -24.989009615867644,
            16.89678262030025
          ],
          [
            -24.98888086983493,
            16.896749256865895
          ],
          [
            -24.988317605941802,
            16.89783228226023
          ],
          [
            -24.987333235233336,
            16.897963168794266
          ],
          [
            -24.987395509354656,
            16.898536157830822
          ]
        ],
        "type": "LineString"
      },
      "id": "f5571553-e63c-493b-aac6-f09445cc3d00"
    }
  ]
}